weskit_client/__init__.py
weskit_client/cli.py
weskit_client/com.py
weskit_client/oidc.py
weskit_client/runs.py
weskit_client/service_info.py
weskit_client/workflows.py
weskit_client-1.0.1.dist-info/licenses/LICENSE
weskit_client-1.0.1.dist-info/METADATA
weskit_client-1.0.1.dist-info/WHEEL
weskit_client-1.0.1.dist-info/entry_points.txt
weskit_client-1.0.1.dist-info/top_level.txt
weskit_client-1.0.1.dist-info/RECORD
